<?xml version='1.0' encoding='utf-8'?>
<data>
  <!--NOTE: This is an ** Autogenerated file **-->
  <!--NOTE: Sector size is 512bytes-->
  <program SECTOR_SIZE_IN_BYTES="512" file_sector_offset="0" filename="xbl.elf" label="xbl" num_partition_sectors="7168" partofsingleimage="false" physical_partition_number="0" readbackverify="false" size_in_KB="3584.0" sparse="false" start_byte_hex="0x4000000" start_sector="131072" />
  <program SECTOR_SIZE_IN_BYTES="512" file_sector_offset="0" filename="xbl.elf" label="xblbak" num_partition_sectors="7168" partofsingleimage="false" physical_partition_number="0" readbackverify="false" size_in_KB="3584.0" sparse="false" start_byte_hex="0x4380000" start_sector="138240" />
  <program SECTOR_SIZE_IN_BYTES="512" file_sector_offset="0" filename="tz.mbn" label="tz" num_partition_sectors="8192" partofsingleimage="false" physical_partition_number="0" readbackverify="false" size_in_KB="4096.0" sparse="false" start_byte_hex="0x4700000" start_sector="145408" />
  <program SECTOR_SIZE_IN_BYTES="512" file_sector_offset="0" filename="tz.mbn" label="tzbak" num_partition_sectors="8192" partofsingleimage="false" physical_partition_number="0" readbackverify="false" size_in_KB="4096.0" sparse="false" start_byte_hex="0x4b00000" start_sector="153600" />
  <program SECTOR_SIZE_IN_BYTES="512" file_sector_offset="0" filename="rpm.mbn" label="rpm" num_partition_sectors="1024" partofsingleimage="false" physical_partition_number="0" readbackverify="false" size_in_KB="512.0" sparse="false" start_byte_hex="0x4f00000" start_sector="161792" />
  <program SECTOR_SIZE_IN_BYTES="512" file_sector_offset="0" filename="rpm.mbn" label="rpmbak" num_partition_sectors="1024" partofsingleimage="false" physical_partition_number="0" readbackverify="false" size_in_KB="512.0" sparse="false" start_byte_hex="0x4f80000" start_sector="162816" />
  <program SECTOR_SIZE_IN_BYTES="512" file_sector_offset="0" filename="hyp.mbn" label="hyp" num_partition_sectors="1024" partofsingleimage="false" physical_partition_number="0" readbackverify="false" size_in_KB="512.0" sparse="false" start_byte_hex="0x5000000" start_sector="163840" />
  <program SECTOR_SIZE_IN_BYTES="512" file_sector_offset="0" filename="hyp.mbn" label="hypbak" num_partition_sectors="1024" partofsingleimage="false" physical_partition_number="0" readbackverify="false" size_in_KB="512.0" sparse="false" start_byte_hex="0x5080000" start_sector="164864" />
  <program SECTOR_SIZE_IN_BYTES="512" file_sector_offset="0" filename="pmic.elf" label="pmic" num_partition_sectors="1024" partofsingleimage="false" physical_partition_number="0" readbackverify="false" size_in_KB="512.0" sparse="false" start_byte_hex="0x5100000" start_sector="165888" />
  <program SECTOR_SIZE_IN_BYTES="512" file_sector_offset="0" filename="pmic.elf" label="pmicbak" num_partition_sectors="1024" partofsingleimage="false" physical_partition_number="0" readbackverify="false" size_in_KB="512.0" sparse="false" start_byte_hex="0x5180000" start_sector="166912" />
  <program SECTOR_SIZE_IN_BYTES="512" file_sector_offset="0" filename="" label="fsg" num_partition_sectors="4096" partofsingleimage="false" physical_partition_number="0" readbackverify="false" size_in_KB="2048.0" sparse="false" start_byte_hex="0x5200000" start_sector="167936" />
  <program SECTOR_SIZE_IN_BYTES="512" file_sector_offset="0" filename="boot.img" label="boot" num_partition_sectors="131072" partofsingleimage="false" physical_partition_number="0" readbackverify="false" size_in_KB="65536.0" sparse="false" start_byte_hex="0x8000000" start_sector="262144" />
  <program SECTOR_SIZE_IN_BYTES="512" file_sector_offset="0" filename="system.img" label="system" num_partition_sectors="6291456" partofsingleimage="false" physical_partition_number="0" readbackverify="false" size_in_KB="3145728.0" sparse="true" start_byte_hex="0xc000000" start_sector="393216" />
  <program SECTOR_SIZE_IN_BYTES="512" file_sector_offset="0" filename="vendor.img" label="vendor" num_partition_sectors="4194304" partofsingleimage="false" physical_partition_number="0" readbackverify="false" size_in_KB="2097152.0" sparse="true" start_byte_hex="0xcc000000" start_sector="6684672" />
  <program SECTOR_SIZE_IN_BYTES="512" file_sector_offset="0" filename="keymaster64.mbn" label="keymaster" num_partition_sectors="2048" partofsingleimage="false" physical_partition_number="0" readbackverify="false" size_in_KB="1024.0" sparse="false" start_byte_hex="0x14c000000" start_sector="10878976" />
  <program SECTOR_SIZE_IN_BYTES="512" file_sector_offset="0" filename="keymaster64.mbn" label="keymasterbak" num_partition_sectors="2048" partofsingleimage="false" physical_partition_number="0" readbackverify="false" size_in_KB="1024.0" sparse="false" start_byte_hex="0x14c100000" start_sector="10881024" />
  <program SECTOR_SIZE_IN_BYTES="512" file_sector_offset="0" filename="cmnlib.mbn" label="cmnlib" num_partition_sectors="2048" partofsingleimage="false" physical_partition_number="0" readbackverify="false" size_in_KB="1024.0" sparse="false" start_byte_hex="0x14c200000" start_sector="10883072" />
  <program SECTOR_SIZE_IN_BYTES="512" file_sector_offset="0" filename="cmnlib64.mbn" label="cmnlib64" num_partition_sectors="2048" partofsingleimage="false" physical_partition_number="0" readbackverify="false" size_in_KB="1024.0" sparse="false" start_byte_hex="0x14c300000" start_sector="10885120" />
  <program SECTOR_SIZE_IN_BYTES="512" file_sector_offset="0" filename="cmnlib.mbn" label="cmnlibbak" num_partition_sectors="2048" partofsingleimage="false" physical_partition_number="0" readbackverify="false" size_in_KB="1024.0" sparse="false" start_byte_hex="0x14c400000" start_sector="10887168" />
  <program SECTOR_SIZE_IN_BYTES="512" file_sector_offset="0" filename="cmnlib64.mbn" label="cmnlib64bak" num_partition_sectors="2048" partofsingleimage="false" physical_partition_number="0" readbackverify="false" size_in_KB="1024.0" sparse="false" start_byte_hex="0x14c500000" start_sector="10889216" />
  <program SECTOR_SIZE_IN_BYTES="512" file_sector_offset="0" filename="mdtpsecapp.mbn" label="mdtpsecapp" num_partition_sectors="8192" partofsingleimage="false" physical_partition_number="0" readbackverify="false" size_in_KB="4096.0" sparse="false" start_byte_hex="0x14c600000" start_sector="10891264" />
  <program SECTOR_SIZE_IN_BYTES="512" file_sector_offset="0" filename="mdtpsecapp.mbn" label="mdtpsecappbak" num_partition_sectors="8192" partofsingleimage="false" physical_partition_number="0" readbackverify="false" size_in_KB="4096.0" sparse="false" start_byte_hex="0x14ca00000" start_sector="10899456" />
  <program SECTOR_SIZE_IN_BYTES="512" file_sector_offset="0" filename="mdtp.img" label="mdtp" num_partition_sectors="65536" partofsingleimage="false" physical_partition_number="0" readbackverify="false" size_in_KB="32768.0" sparse="false" start_byte_hex="0x14ce00000" start_sector="10907648" />
  <program SECTOR_SIZE_IN_BYTES="512" file_sector_offset="0" filename="mdtp.img" label="mdtpbak" num_partition_sectors="65536" partofsingleimage="false" physical_partition_number="0" readbackverify="false" size_in_KB="32768.0" sparse="false" start_byte_hex="0x14ee00000" start_sector="10973184" />
  <program SECTOR_SIZE_IN_BYTES="512" file_sector_offset="0" filename="NON-HLOS.bin" label="modem" num_partition_sectors="524288" partofsingleimage="false" physical_partition_number="0" readbackverify="false" size_in_KB="262144.0" sparse="false" start_byte_hex="0x150e00000" start_sector="11038720" />
  <program SECTOR_SIZE_IN_BYTES="512" file_sector_offset="0" filename="NON-HLOS.bin" label="modembak" num_partition_sectors="524288" partofsingleimage="false" physical_partition_number="0" readbackverify="false" size_in_KB="262144.0" sparse="false" start_byte_hex="0x160e00000" start_sector="11563008" />
  <program SECTOR_SIZE_IN_BYTES="512" file_sector_offset="0" filename="dspso.bin" label="dsp" num_partition_sectors="32768" partofsingleimage="false" physical_partition_number="0" readbackverify="false" size_in_KB="16384.0" sparse="false" start_byte_hex="0x170e00000" start_sector="12087296" />
  <program SECTOR_SIZE_IN_BYTES="512" file_sector_offset="0" filename="dspso.bin" label="dspbak" num_partition_sectors="32768" partofsingleimage="false" physical_partition_number="0" readbackverify="false" size_in_KB="16384.0" sparse="false" start_byte_hex="0x171e00000" start_sector="12120064" />
  <program SECTOR_SIZE_IN_BYTES="512" file_sector_offset="0" filename="abl.elf" label="abl" num_partition_sectors="2048" partofsingleimage="false" physical_partition_number="0" readbackverify="false" size_in_KB="1024.0" sparse="false" start_byte_hex="0x172e00000" start_sector="12152832" />
  <program SECTOR_SIZE_IN_BYTES="512" file_sector_offset="0" filename="abl.elf" label="ablbak" num_partition_sectors="2048" partofsingleimage="false" physical_partition_number="0" readbackverify="false" size_in_KB="1024.0" sparse="false" start_byte_hex="0x172f00000" start_sector="12154880" />
  <program SECTOR_SIZE_IN_BYTES="512" file_sector_offset="0" filename="" label="dip" num_partition_sectors="2048" partofsingleimage="false" physical_partition_number="0" readbackverify="false" size_in_KB="1024.0" sparse="false" start_byte_hex="0x173000000" start_sector="12156928" />
  <program SECTOR_SIZE_IN_BYTES="512" file_sector_offset="0" filename="" label="devinfo" num_partition_sectors="8" partofsingleimage="false" physical_partition_number="0" readbackverify="false" size_in_KB="4.0" sparse="false" start_byte_hex="0x173100000" start_sector="12158976" />
  <program SECTOR_SIZE_IN_BYTES="512" file_sector_offset="0" filename="dp_AP_signed.mbn" label="apdp" num_partition_sectors="512" partofsingleimage="false" physical_partition_number="0" readbackverify="false" size_in_KB="256.0" sparse="false" start_byte_hex="0x173101000" start_sector="12158984" />
  <program SECTOR_SIZE_IN_BYTES="512" file_sector_offset="0" filename="dp_MSA_signed.mbn" label="msadp" num_partition_sectors="512" partofsingleimage="false" physical_partition_number="0" readbackverify="false" size_in_KB="256.0" sparse="false" start_byte_hex="0x173141000" start_sector="12159496" />
  <program SECTOR_SIZE_IN_BYTES="512" file_sector_offset="0" filename="" label="dpo" num_partition_sectors="2" partofsingleimage="false" physical_partition_number="0" readbackverify="false" size_in_KB="1.0" sparse="false" start_byte_hex="0x173181000" start_sector="12160008" />
  <program SECTOR_SIZE_IN_BYTES="512" file_sector_offset="0" filename="splash.img" label="splash" num_partition_sectors="66848" partofsingleimage="false" physical_partition_number="0" readbackverify="false" size_in_KB="33424.0" sparse="false" start_byte_hex="0x173182000" start_sector="12160016" />
  <program SECTOR_SIZE_IN_BYTES="512" file_sector_offset="0" filename="" label="limits" num_partition_sectors="8" partofsingleimage="false" physical_partition_number="0" readbackverify="false" size_in_KB="4.0" sparse="false" start_byte_hex="0x175226000" start_sector="12226864" />
  <program SECTOR_SIZE_IN_BYTES="512" file_sector_offset="0" filename="" label="toolsfv" num_partition_sectors="2048" partofsingleimage="false" physical_partition_number="0" readbackverify="false" size_in_KB="1024.0" sparse="false" start_byte_hex="0x175227000" start_sector="12226872" />
  <program SECTOR_SIZE_IN_BYTES="512" file_sector_offset="0" filename="" label="logfs" num_partition_sectors="16384" partofsingleimage="false" physical_partition_number="0" readbackverify="false" size_in_KB="8192.0" sparse="false" start_byte_hex="0x178000000" start_sector="12320768" />
  <program SECTOR_SIZE_IN_BYTES="512" file_sector_offset="0" filename="" label="ddr" num_partition_sectors="2048" partofsingleimage="false" physical_partition_number="0" readbackverify="false" size_in_KB="1024.0" sparse="false" start_byte_hex="0x17c000000" start_sector="12451840" />
  <program SECTOR_SIZE_IN_BYTES="512" file_sector_offset="0" filename="sec.dat" label="sec" num_partition_sectors="32" partofsingleimage="false" physical_partition_number="0" readbackverify="false" size_in_KB="16.0" sparse="false" start_byte_hex="0x17c100000" start_sector="12453888" />
  <program SECTOR_SIZE_IN_BYTES="512" file_sector_offset="0" filename="BTFM.bin" label="bluetooth" num_partition_sectors="2048" partofsingleimage="false" physical_partition_number="0" readbackverify="false" size_in_KB="1024.0" sparse="false" start_byte_hex="0x17c104000" start_sector="12453920" />
  <program SECTOR_SIZE_IN_BYTES="512" file_sector_offset="0" filename="BTFM.bin" label="bluetoothbak" num_partition_sectors="2048" partofsingleimage="false" physical_partition_number="0" readbackverify="false" size_in_KB="1024.0" sparse="false" start_byte_hex="0x17c204000" start_sector="12455968" />
  <program SECTOR_SIZE_IN_BYTES="512" file_sector_offset="0" filename="" label="fsc" num_partition_sectors="2" partofsingleimage="false" physical_partition_number="0" readbackverify="false" size_in_KB="1.0" sparse="false" start_byte_hex="0x180000000" start_sector="12582912" />
  <program SECTOR_SIZE_IN_BYTES="512" file_sector_offset="0" filename="" label="ssd" num_partition_sectors="16" partofsingleimage="false" physical_partition_number="0" readbackverify="false" size_in_KB="8.0" sparse="false" start_byte_hex="0x180001000" start_sector="12582920" />
  <program SECTOR_SIZE_IN_BYTES="512" file_sector_offset="0" filename="" label="modemst1" num_partition_sectors="4096" partofsingleimage="false" physical_partition_number="0" readbackverify="false" size_in_KB="2048.0" sparse="false" start_byte_hex="0x180003000" start_sector="12582936" />
  <program SECTOR_SIZE_IN_BYTES="512" file_sector_offset="0" filename="" label="modemst2" num_partition_sectors="4096" partofsingleimage="false" physical_partition_number="0" readbackverify="false" size_in_KB="2048.0" sparse="false" start_byte_hex="0x180203000" start_sector="12587032" />
  <program SECTOR_SIZE_IN_BYTES="512" file_sector_offset="0" filename="" label="persist" num_partition_sectors="65536" partofsingleimage="false" physical_partition_number="0" readbackverify="false" size_in_KB="32768.0" sparse="false" start_byte_hex="0x180403000" start_sector="12591128" />
  <program SECTOR_SIZE_IN_BYTES="512" file_sector_offset="0" filename="cache.img" label="cache" num_partition_sectors="524288" partofsingleimage="false" physical_partition_number="0" readbackverify="false" size_in_KB="262144.0" sparse="true" start_byte_hex="0x182403000" start_sector="12656664" />
  <program SECTOR_SIZE_IN_BYTES="512" file_sector_offset="0" filename="zeros_2048sectors.bin" label="misc" num_partition_sectors="2048" partofsingleimage="false" physical_partition_number="0" readbackverify="false" size_in_KB="1024.0" sparse="false" start_byte_hex="0x192403000" start_sector="13180952" />
  <program SECTOR_SIZE_IN_BYTES="512" file_sector_offset="0" filename="recovery.img" label="recovery" num_partition_sectors="131072" partofsingleimage="false" physical_partition_number="0" readbackverify="false" size_in_KB="65536.0" sparse="false" start_byte_hex="0x192503000" start_sector="13183000" />
  <program SECTOR_SIZE_IN_BYTES="512" file_sector_offset="0" filename="" label="keystore" num_partition_sectors="1024" partofsingleimage="false" physical_partition_number="0" readbackverify="false" size_in_KB="512.0" sparse="false" start_byte_hex="0x196503000" start_sector="13314072" />
  <program SECTOR_SIZE_IN_BYTES="512" file_sector_offset="0" filename="devcfg.mbn" label="devcfg" num_partition_sectors="2048" partofsingleimage="false" physical_partition_number="0" readbackverify="false" size_in_KB="1024.0" sparse="false" start_byte_hex="0x196583000" start_sector="13315096" />
  <program SECTOR_SIZE_IN_BYTES="512" file_sector_offset="0" filename="devcfg.mbn" label="devcfgbak" num_partition_sectors="2048" partofsingleimage="false" physical_partition_number="0" readbackverify="false" size_in_KB="1024.0" sparse="false" start_byte_hex="0x196683000" start_sector="13317144" />
  <program SECTOR_SIZE_IN_BYTES="512" file_sector_offset="0" filename="zeros_1024sectors.bin" label="frp" num_partition_sectors="1024" partofsingleimage="false" physical_partition_number="0" readbackverify="false" size_in_KB="512.0" sparse="false" start_byte_hex="0x196783000" start_sector="13319192" />
  <program SECTOR_SIZE_IN_BYTES="512" file_sector_offset="0" filename="" label="logdump" num_partition_sectors="131072" partofsingleimage="false" physical_partition_number="0" readbackverify="false" size_in_KB="65536.0" sparse="false" start_byte_hex="0x196803000" start_sector="13320216" />
  <program SECTOR_SIZE_IN_BYTES="512" file_sector_offset="0" filename="" label="sti" num_partition_sectors="4096" partofsingleimage="false" physical_partition_number="0" readbackverify="false" size_in_KB="2048.0" sparse="false" start_byte_hex="0x19a803000" start_sector="13451288" />
  <program SECTOR_SIZE_IN_BYTES="512" file_sector_offset="0" filename="storsec.mbn" label="storsec" num_partition_sectors="256" partofsingleimage="false" physical_partition_number="0" readbackverify="false" size_in_KB="128.0" sparse="false" start_byte_hex="0x19c000000" start_sector="13500416" />
  <program SECTOR_SIZE_IN_BYTES="512" file_sector_offset="0" filename="" label="rawdump" num_partition_sectors="262144" partofsingleimage="false" physical_partition_number="0" readbackverify="false" size_in_KB="131072.0" sparse="false" start_byte_hex="0x1a0000000" start_sector="13631488" />
  <program SECTOR_SIZE_IN_BYTES="512" file_sector_offset="0" filename="" label="vbmeta" num_partition_sectors="128" partofsingleimage="false" physical_partition_number="0" readbackverify="false" size_in_KB="64.0" sparse="false" start_byte_hex="0x1a8000000" start_sector="13893632" />
  <program SECTOR_SIZE_IN_BYTES="512" file_sector_offset="0" filename="" label="vbmetabak" num_partition_sectors="128" partofsingleimage="false" physical_partition_number="0" readbackverify="false" size_in_KB="64.0" sparse="false" start_byte_hex="0x1a8010000" start_sector="13893760" />
  <program SECTOR_SIZE_IN_BYTES="512" file_sector_offset="0" filename="cust.img" label="cust" num_partition_sectors="1703936" partofsingleimage="false" physical_partition_number="0" readbackverify="false" size_in_KB="851968.0" sparse="true" start_byte_hex="0x1ac000000" start_sector="14024704" />
  <program SECTOR_SIZE_IN_BYTES="512" file_sector_offset="0" filename="logo.img" label="logo" num_partition_sectors="66848" partofsingleimage="false" physical_partition_number="0" readbackverify="false" size_in_KB="33424.0" sparse="false" start_byte_hex="0x1e0000000" start_sector="15728640" />
  <program SECTOR_SIZE_IN_BYTES="512" file_sector_offset="0" filename="userdata.img" label="userdata" num_partition_sectors="0" partofsingleimage="false" physical_partition_number="0" readbackverify="false" size_in_KB="0" sparse="true" start_byte_hex="0x1e20a4000" start_sector="15795488" />
  <program SECTOR_SIZE_IN_BYTES="512" file_sector_offset="0" filename="gpt_main0.bin" label="PrimaryGPT" num_partition_sectors="34" partofsingleimage="true" physical_partition_number="0" readbackverify="false" size_in_KB="17.0" sparse="false" start_byte_hex="0x0" start_sector="0" />
  <program SECTOR_SIZE_IN_BYTES="512" file_sector_offset="0" filename="gpt_backup0.bin" label="BackupGPT" num_partition_sectors="33" partofsingleimage="true" physical_partition_number="0" readbackverify="false" size_in_KB="16.5" sparse="false" start_byte_hex="(512*NUM_DISK_SECTORS)-16896." start_sector="NUM_DISK_SECTORS-33." />
</data>